LICENSE
MANIFEST.in
README.rst
setup.cfg
setup.py
account/__init__.py
account/admin.py
account/apps.py
account/forms.py
account/models.py
account/tests.py
account/urls.py
account/utils.py
account/views.py
account/migrations/__init__.py
django_pass_code.egg-info/PKG-INFO
django_pass_code.egg-info/SOURCES.txt
django_pass_code.egg-info/dependency_links.txt
django_pass_code.egg-info/top_level.txt